{
  "resourceType": "Observation",
  "id": "3554646",
  "meta": {
    "versionId": "1",
    "lastUpdated": "2026-03-23T05:11:15.195-04:00",
    "security": [
      {
        "system": "http://cibmtr.org/codesystem/transplant-center",
        "code": "rc_12001"
      }
    ]
  },
  "status": "final",
  "category": [
    {
      "coding": [
        {
          "system": "http://hl7.org/fhir/observation-category",
          "code": "vital-signs",
          "display": "vital-signs"
        }
      ],
      "text": "The results of observations generated by laboratories."
    }
  ],
  "code": {
    "coding": [
      {
        "system": "https://loinc.org",
        "code": "29463-7",
        "display": "Weight Change at Post Infusion"
      }
    ],
    "text": "Weight"
  },
  "subject": {
    "reference": "Patient/3554616"
  },
  "effectiveDateTime": "2013-06-26T18:33:00+00:00",
  "valueQuantity": {
    "value": 20.3,
    "unit": "kg",
    "system": "http://unitsofmeasure.org",
    "code": "kg"
  },
  "ingestion_timestamp": "2026-03-24T05:52:59.831305",
  "ingestion_date": "2026-03-24"
}