{
  "resourceType": "Observation",
  "id": "c4a841e3-a45a-4571-b413-161ed79c0f44",
  "meta": {
    "versionId": "4",
    "lastUpdated": "2021-04-06T03:01:32.646-04:00",
    "tag": [
      {
        "system": "https://smarthealthit.org/tags",
        "code": "synthea-5-2019"
      }
    ]
  },
  "status": "final",
  "category": [
    {
      "coding": [
        {
          "system": "http://terminology.hl7.org/CodeSystem/observation-category",
          "code": "laboratory",
          "display": "laboratory"
        }
      ]
    }
  ],
  "code": {
    "coding": [
      {
        "system": "http://loinc.org",
        "code": "2339-0",
        "display": "Glucose"
      }
    ],
    "text": "Glucose"
  },
  "subject": {
    "reference": "Patient/0ac13d55-d566-450a-aea0-f6a71f1ad73b"
  },
  "encounter": {
    "reference": "Encounter/5f6910e0-8527-40d0-8fc6-04aac352285b"
  },
  "effectiveDateTime": "2008-11-10T12:17:10+00:00",
  "issued": "2008-11-10T12:17:10.817+00:00",
  "valueQuantity": {
    "value": 84.79363832632752,
    "unit": "mg/dL",
    "system": "http://unitsofmeasure.org",
    "code": "mg/dL"
  }
}