{
  "resourceType": "MedicationRequest",
  "id": "60bc5ed1-b9cd-46e9-b250-32b4c297ad0c",
  "meta": {
    "versionId": "5",
    "lastUpdated": "2025-09-24T03:09:42.951-04:00",
    "tag": [
      {
        "system": "https://smarthealthit.org/tags",
        "code": "synthea-5-2019"
      }
    ]
  },
  "status": "stopped",
  "intent": "order",
  "medicationCodeableConcept": {
    "coding": [
      {
        "system": "http://www.nlm.nih.gov/research/umls/rxnorm",
        "code": "1094107",
        "display": "Phenazopyridine hydrochloride 100 MG Oral Tablet"
      }
    ],
    "text": "Phenazopyridine hydrochloride 100 MG Oral Tablet"
  },
  "subject": {
    "reference": "Patient/4db03e6a-a8d0-4691-b861-e685e90a5d77"
  },
  "encounter": {
    "reference": "Encounter/a6c81b53-782e-4933-bc08-9f8bc04f4293"
  },
  "authoredOn": "2019-07-17T07:53:26+00:00",
  "requester": {
    "reference": "Practitioner/8b85559d-27de-4d4b-bea7-5a715164cb60"
  },
  "reasonReference": [
    {
      "reference": "Condition/5a7fe38c-9cb7-42fd-9209-a44422dc74be"
    }
  ],
  "ingestion_timestamp": "2026-03-24T05:53:04.952851",
  "ingestion_date": "2026-03-24"
}