{
  "resourceType": "MedicationRequest",
  "id": "359e4780-c914-4c71-b035-277f96be8e27",
  "meta": {
    "versionId": "26",
    "lastUpdated": "2026-02-21T02:22:59.755-05:00",
    "tag": [
      {
        "system": "https://smarthealthit.org/tags",
        "code": "synthea-5-2019"
      }
    ]
  },
  "status": "stopped",
  "intent": "order",
  "medicationCodeableConcept": {
    "coding": [
      {
        "system": "http://www.nlm.nih.gov/research/umls/rxnorm",
        "code": "1367439",
        "display": "NuvaRing 0.12/0.015 MG per 24HR 21 Day Vaginal Ring"
      }
    ],
    "text": "NuvaRing 0.12/0.015 MG per 24HR 21 Day Vaginal Ring"
  },
  "subject": {
    "reference": "Patient/775ae455-7966-416e-8d04-fd0b8fdac28f"
  },
  "encounter": {
    "reference": "Encounter/ee2b26f2-f956-455a-94b0-9a69e6eaa1a6"
  },
  "authoredOn": "2015-11-16T22:56:38+00:00",
  "requester": {
    "reference": "Practitioner/79a13b7d-a382-4b6a-a31a-57e763818a56"
  },
  "ingestion_timestamp": "2026-03-24T05:53:04.963403",
  "ingestion_date": "2026-03-24"
}